{
  "AR": "Argentinië",
  "BO": "Bolivië",
  "BR": "Brasilië",
  "CL": "Chili",
  "CO": "Colombië",
  "EC": "Ecuador",
  "FK": "Falklandeilande",
  "FK-variant": "Falklandeilande (Malvinas)",
  "GF": "Frans-Guyana",
  "GY": "Guyana",
  "PE": "Peru",
  "PY": "Paraguay",
  "SR": "Suriname",
  "UY": "Uruguay",
  "VE": "Venezuela",
  "AE": "Verenigde Arabiese Emirate",
  "AM": "Armenië",
  "AZ": "Azerbeidjan",
  "BH": "Bahrein",
  "CY": "Siprus",
  "GE": "Georgië",
  "IL": "Israel",
  "IQ": "Irak",
  "JO": "Jordanië",
  "KW": "Koeweit",
  "LB": "Libanon",
  "OM": "Oman",
  "PS": "Palestynse gebiede",
  "PS-short": "Palestina",
  "QA": "Katar",
  "SA": "Saoedi-Arabië",
  "SY": "Sirië",
  "TR": "Turkye",
  "YE": "Jemen",
  "TM": "Turkmenië",
  "TJ": "Tadjikistan",
  "KG": "Kirgisië",
  "KZ": "Kazakstan",
  "UZ": "Oesbekistan",
  "CN": "Sjina",
  "HK": "Hongkong SAS Sjina",
  "HK-short": "Hongkong",
  "JP": "Japan",
  "KP": "Noord-Korea",
  "KR": "Suid-Korea",
  "MN": "Mongolië",
  "MO": "Macau SAS Sjina",
  "MO-short": "Macau",
  "TW": "Taiwan",
  "AF": "Afganistan",
  "BD": "Bangladesj",
  "BT": "Bhoetan",
  "IN": "Indië",
  "IR": "Iran",
  "LK": "Sri Lanka",
  "MV": "Maledive",
  "NP": "Nepal",
  "PK": "Pakistan",
  "BN": "Broenei",
  "ID": "Indonesië",
  "KH": "Kambodja",
  "LA": "Laos",
  "MM": "Mianmar (Birma)",
  "MY": "Maleisië",
  "PH": "Filippyne",
  "SG": "Singapoer",
  "TH": "Thailand",
  "TL": "Oos-Timor",
  "VN": "Viëtnam",
  "BM": "Bermuda",
  "CA": "Kanada",
  "GL": "Groenland",
  "PM": "St. Pierre en Miquelon",
  "US": "Verenigde State van Amerika",
  "US-short": "VSA",
  "BZ": "Belize",
  "CR": "Costa Rica",
  "GT": "Guatemala",
  "HN": "Honduras",
  "MX": "Meksiko",
  "NI": "Nicaragua",
  "PA": "Panama",
  "SV": "El Salvador",
  "AG": "Antigua en Barbuda",
  "AI": "Anguilla",
  "AW": "Aruba",
  "BB": "Barbados",
  "BL": "Sint Barthélemy",
  "BQ": "Karibiese Nederland",
  "BS": "Bahamas",
  "CU": "Kuba",
  "CW": "Curaçao",
  "DM": "Dominica",
  "DO": "Dominikaanse Republiek",
  "GD": "Grenada",
  "GP": "Guadeloupe",
  "HT": "Haïti",
  "JM": "Jamaika",
  "KN": "St. Kitts en Nevis",
  "KY": "Kaaimanseilande",
  "LC": "St. Lucia",
  "MF": "St. Martin",
  "MQ": "Martinique",
  "MS": "Montserrat",
  "PR": "Puerto Rico",
  "SX": "Sint Maarten",
  "TC": "Turks- en Caicoseilande",
  "TT": "Trinidad en Tobago",
  "VC": "St. Vincent en die Grenadine",
  "VG": "Britse Maagde-eilande",
  "VI": "Amerikaanse Maagde-eilande",
  "GG": "Guernsey",
  "IM": "Eiland Man",
  "JE": "Jersey",
  "AX": "Ålandeilande",
  "DK": "Denemarke",
  "EE": "Estland",
  "FI": "Finland",
  "FO": "Faroëreilande",
  "GB": "Verenigde Koninkryk",
  "GB-short": "VK",
  "IE": "Ierland",
  "IS": "Ysland",
  "LT": "Litaue",
  "LV": "Letland",
  "NO": "Noorweë",
  "SE": "Swede",
  "SJ": "Svalbard en Jan Mayen",
  "AT": "Oostenryk",
  "BE": "België",
  "CH": "Switserland",
  "DE": "Duitsland",
  "FR": "Frankryk",
  "LI": "Liechtenstein",
  "LU": "Luxemburg",
  "MC": "Monaco",
  "NL": "Nederland",
  "BG": "Bulgarye",
  "BY": "Belarus",
  "CZ": "Tjeggië",
  "CZ-variant": "Tjeggiese Republiek",
  "HU": "Hongarye",
  "MD": "Moldowa",
  "PL": "Pole",
  "RO": "Roemenië",
  "RU": "Rusland",
  "SK": "Slowakye",
  "UA": "Oekraïne",
  "AD": "Andorra",
  "AL": "Albanië",
  "BA": "Bosnië en Herzegowina",
  "ES": "Spanje",
  "GI": "Gibraltar",
  "GR": "Griekeland",
  "HR": "Kroasië",
  "IT": "Italië",
  "ME": "Montenegro",
  "MK": "Macedonië",
  "MK-variant": "Macedonië (VJRM)",
  "MT": "Malta",
  "RS": "Serwië",
  "PT": "Portugal",
  "SI": "Slowenië",
  "SM": "San Marino",
  "VA": "Vatikaanstad",
  "XK": "Kosovo",
  "DZ": "Algerië",
  "EG": "Egipte",
  "EH": "Wes-Sahara",
  "LY": "Libië",
  "MA": "Marokko",
  "SD": "Soedan",
  "TN": "Tunisië",
  "EA": "Ceuta en Melilla",
  "IC": "Kanariese Eilande",
  "BF": "Burkina Faso",
  "BJ": "Benin",
  "CI": "Ivoorkus",
  "CV": "Kaap Verde",
  "GH": "Ghana",
  "GM": "Gambië",
  "GN": "Guinee",
  "GW": "Guinee-Bissau",
  "LR": "Liberië",
  "ML": "Mali",
  "MR": "Mauritanië",
  "NE": "Niger",
  "NG": "Nigerië",
  "SH": "Sint Helena",
  "SL": "Sierra Leone",
  "SN": "Senegal",
  "TG": "Togo",
  "AO": "Angola",
  "CD": "Demokratiese Republiek van die Kongo",
  "CD-variant": "Kongo (DRK)",
  "CF": "Sentraal-Afrikaanse Republiek",
  "CG": "Kongo - Brazzaville",
  "CG-variant": "Kongo (Republiek die)",
  "CM": "Kameroen",
  "GA": "Gaboen",
  "GQ": "Ekwatoriaal-Guinee",
  "ST": "São Tomé en Príncipe",
  "TD": "Tsjad",
  "BI": "Burundi",
  "DJ": "Djiboeti",
  "ER": "Eritrea",
  "ET": "Ethiopië",
  "KE": "Kenia",
  "KM": "Comore",
  "MG": "Madagaskar",
  "MU": "Mauritius",
  "MW": "Malawi",
  "MZ": "Mosambiek",
  "RE": "Réunion",
  "RW": "Rwanda",
  "SC": "Seychelle",
  "SO": "Somalië",
  "SS": "Suid-Soedan",
  "TZ": "Tanzanië",
  "UG": "Uganda",
  "YT": "Mayotte",
  "ZM": "Zambië",
  "ZW": "Zimbabwe",
  "BW": "Botswana",
  "LS": "Lesotho",
  "NA": "Namibië",
  "SZ": "Swaziland",
  "ZA": "Suid-Afrika",
  "AU": "Australië",
  "NF": "Norfolkeiland",
  "NZ": "Nieu-Seeland",
  "FJ": "Fidji",
  "NC": "Nieu-Kaledonië",
  "PG": "Papoea-Nieu-Guinee",
  "SB": "Salomonseilande",
  "VU": "Vanuatu",
  "FM": "Mikronesië",
  "GU": "Guam",
  "KI": "Kiribati",
  "MH": "Marshalleilande",
  "MP": "Noord-Mariane-eilande",
  "NR": "Nauru",
  "PW": "Palau",
  "AS": "Amerikaans-Samoa",
  "CK": "Cookeilande",
  "NU": "Niue",
  "PF": "Frans-Polinesië",
  "PN": "Pitcairneilande",
  "TK": "Tokelau",
  "TO": "Tonga",
  "TV": "Tuvalu",
  "WF": "Wallis en Futuna",
  "WS": "Samoa",
  "AQ": "Antarktika",
  "BV": "Bouvet-eiland",
  "CC": "Kokos-eilande",
  "CX": "Kerseiland",
  "GS": "Suid-Georgië en die Suidelike Sandwicheilande",
  "HM": "Heard- en McDonaldeilande",
  "IO": "Brits-Indiese Oseaangebied",
  "TF": "Franse Suidelike Gebiede",
  "UM": "VS klein omliggende eilande",
  "AC": "Ascensioneiland",
  "CP": "Clippertoneiland",
  "DG": "Diego Garcia",
  "TA": "Tristan da Cunha"
}